unionmeta_byoc/__init__.py
unionmeta_byoc-0.1.0.dist-info/APL.txt
unionmeta_byoc-0.1.0.dist-info/BSL.txt
unionmeta_byoc-0.1.0.dist-info/LICENSE
unionmeta_byoc-0.1.0.dist-info/METADATA
unionmeta_byoc-0.1.0.dist-info/WHEEL
unionmeta_byoc-0.1.0.dist-info/top_level.txt
unionmeta_byoc-0.1.0.dist-info/RECORD
