Metadata-Version: 2.1
Name: unionmeta-byoc
Version: 0.1.0
Summary: Adds Union meta library for the Union.ai SDK
Author-email: unionai <info@union.ai>
License: Source code in this repository is licensed under the Business Source
Project-URL: Homepage, https://www.union.ai/
Classifier: Intended Audience :: Science/Research
Classifier: Intended Audience :: Developers
Classifier: License :: Other/Proprietary License
Classifier: Programming Language :: Python :: 3
Classifier: Topic :: Scientific/Engineering
Classifier: Topic :: Scientific/Engineering :: Artificial Intelligence
Classifier: Topic :: Software Development
Classifier: Topic :: Software Development :: Libraries
Classifier: Topic :: Software Development :: Libraries :: Python Modules
License-File: licenses/APL.txt
License-File: licenses/BSL.txt
License-File: LICENSE
